_kratos.cp38-win_amd64.pyd
kratos/__init__.py
kratos/debug.py
kratos/formal.py
kratos/fsm.py
kratos/func.py
kratos/generator.py
kratos/interface.py
kratos/lib.py
kratos/passes.py
kratos/ports.py
kratos/pyast.py
kratos/sim.py
kratos/stmts.py
kratos/tb.py
kratos/util.py
kratos-0.1.3.dist-info/LICENSE
kratos-0.1.3.dist-info/METADATA
kratos-0.1.3.dist-info/WHEEL
kratos-0.1.3.dist-info/top_level.txt
kratos-0.1.3.dist-info/RECORD
