Metadata-Version: 2.1
Name: kratos
Version: 0.1.3
Summary: Kratos is a fast hardware design language embedded in Python
Home-page: https://github.com/Kuree/kratos
Author: Keyi Zhang
Author-email: keyi@stanford.edu
License: UNKNOWN
Platform: UNKNOWN
Requires-Python: >=3.6
Requires-Dist: astor
